CMakeLists.txt
LICENSE
MANIFEST.in
README.rst
setup.py
data/cube.obj
data/girl.obj
data/sveta.obj
examples/pyglet_demo.py
examples/vtk_demo.py
lib/pybind11/CMakeLists.txt
lib/pybind11/include/pybind11/attr.h
lib/pybind11/include/pybind11/buffer_info.h
lib/pybind11/include/pybind11/cast.h
lib/pybind11/include/pybind11/chrono.h
lib/pybind11/include/pybind11/common.h
lib/pybind11/include/pybind11/complex.h
lib/pybind11/include/pybind11/eigen.h
lib/pybind11/include/pybind11/embed.h
lib/pybind11/include/pybind11/eval.h
lib/pybind11/include/pybind11/functional.h
lib/pybind11/include/pybind11/iostream.h
lib/pybind11/include/pybind11/numpy.h
lib/pybind11/include/pybind11/operators.h
lib/pybind11/include/pybind11/options.h
lib/pybind11/include/pybind11/pybind11.h
lib/pybind11/include/pybind11/pytypes.h
lib/pybind11/include/pybind11/stl.h
lib/pybind11/include/pybind11/stl_bind.h
lib/pybind11/include/pybind11/detail/class.h
lib/pybind11/include/pybind11/detail/common.h
lib/pybind11/include/pybind11/detail/descr.h
lib/pybind11/include/pybind11/detail/init.h
lib/pybind11/include/pybind11/detail/internals.h
lib/pybind11/include/pybind11/detail/typeid.h
lib/pybind11/tests/CMakeLists.txt
lib/pybind11/tests/test_cmake_build/CMakeLists.txt
lib/pybind11/tests/test_cmake_build/installed_embed/CMakeLists.txt
lib/pybind11/tests/test_cmake_build/installed_function/CMakeLists.txt
lib/pybind11/tests/test_cmake_build/installed_target/CMakeLists.txt
lib/pybind11/tests/test_cmake_build/subdirectory_embed/CMakeLists.txt
lib/pybind11/tests/test_cmake_build/subdirectory_function/CMakeLists.txt
lib/pybind11/tests/test_cmake_build/subdirectory_target/CMakeLists.txt
lib/pybind11/tests/test_embed/CMakeLists.txt
lib/pybind11/tools/FindCatch.cmake
lib/pybind11/tools/FindEigen3.cmake
lib/pybind11/tools/FindPythonLibsNew.cmake
lib/pybind11/tools/pybind11Tools.cmake
src/attachment.cpp
src/attachment.h
src/bindings.cpp
src/debugging.h
src/deriv.h
src/discretization.cpp
src/dtree.h
src/embedding.cpp
src/pynocchio.egg-info/PKG-INFO
src/pynocchio.egg-info/SOURCES.txt
src/pynocchio.egg-info/dependency_links.txt
src/pynocchio.egg-info/not-zip-safe
src/pynocchio.egg-info/top_level.txt