Metadata-Version: 1.0
Name: pynocchio
Version: 0.0.1
Summary: The pinocchio extension library
Home-page: UNKNOWN
Author: Alexander Larin
Author-email: ekzebox@gmail.com
License: UNKNOWN
Platform: UNKNOWN
